[
    {
        "departure": "Paris ",
        "departure_date": "20 octobre",
        "destination": "Lyon",
        "group_type": "Entreprise",
        "passengers": "20",
        "return_date": "30 actobre",
        "special_needs": "non",
        "trip_type": "allez simple",
        "email": "virgileader&gmail.com",
        "timestamp": "2025-04-18T15:28:52.261195"
    },
    {
        "departure": "PAris",
        "departure_date": "paris",
        "destination": "paris",
        "group_type": "paris",
        "passengers": "paris",
        "return_date": "paris",
        "special_needs": "paris",
        "trip_type": "paris",
        "email": "paris",
        "timestamp": "2025-04-18T15:45:13.366004"
    },
    {
        "departure": "PAris",
        "departure_date": "paris",
        "destination": "paris",
        "group_type": "paris",
        "passengers": "paris",
        "return_date": "paris",
        "special_needs": "paris",
        "trip_type": "paris",
        "email": "paris",
        "timestamp": "2025-04-18T15:46:37.933871"
    },
    {
        "departure": "PAris",
        "departure_date": "paris",
        "destination": "paris",
        "group_type": "paris",
        "passengers": "paris",
        "return_date": "paris",
        "special_needs": "paris",
        "trip_type": "paris",
        "email": "virgileader@gmail.com",
        "timestamp": "2025-04-18T15:46:53.469790"
    },
    {
        "departure": "PAris",
        "departure_date": "paris",
        "destination": "paris",
        "group_type": "paris",
        "passengers": "paris",
        "return_date": "paris",
        "special_needs": "paris",
        "trip_type": "paris",
        "email": "virgileader@gmail.com",
        "timestamp": "2025-04-18T15:46:58.769731"
    },
    {
        "departure": "PAris",
        "departure_date": "paris",
        "destination": "paris",
        "group_type": "paris",
        "passengers": "paris",
        "return_date": "paris",
        "special_needs": "paris",
        "trip_type": "paris",
        "email": "virgileader@gmail.com",
        "timestamp": "2025-04-18T15:47:02.185135"
    },
    {
        "departure": "PAris",
        "departure_date": "paris",
        "destination": "paris",
        "group_type": "paris",
        "passengers": "paris",
        "return_date": "paris",
        "special_needs": "paris",
        "trip_type": "paris",
        "email": "paris",
        "timestamp": "2025-04-18T15:47:28.866432"
    },
    {
        "departure": "PAris",
        "departure_date": "paris",
        "destination": "paris",
        "group_type": "paris",
        "passengers": "paris",
        "return_date": "paris",
        "special_needs": "paris",
        "trip_type": "paris",
        "email": "paris",
        "timestamp": "2025-04-18T15:48:08.920957"
    },
    {
        "departure": "PAris",
        "departure_date": "paris",
        "destination": "paris",
        "group_type": "paris",
        "passengers": "paris",
        "return_date": "paris",
        "special_needs": "paris",
        "trip_type": "paris",
        "email": "paris",
        "timestamp": "2025-04-18T15:48:13.170416"
    },
    {
        "departure": "PAris",
        "departure_date": "paris",
        "destination": "paris",
        "group_type": "paris",
        "passengers": "paris",
        "return_date": "paris",
        "special_needs": "paris",
        "trip_type": "paris",
        "email": "paris",
        "timestamp": "2025-04-18T15:48:15.471259"
    },
    {
        "departure": "PAris",
        "departure_date": "paris",
        "destination": "paris",
        "group_type": "paris",
        "passengers": "paris",
        "return_date": "paris",
        "special_needs": "paris",
        "trip_type": "paris",
        "email": "paris",
        "timestamp": "2025-04-18T15:48:45.159785"
    },
    {
        "departure": "PAris",
        "departure_date": "paris",
        "destination": "paris",
        "group_type": "paris",
        "passengers": "paris",
        "return_date": "paris",
        "special_needs": "paris",
        "trip_type": "paris",
        "email": "paris",
        "timestamp": "2025-04-18T15:49:40.053992"
    },
    {
        "departure": "paris",
        "departure_date": "20 octobre",
        "destination": "paris ",
        "group_type": "Entreprise",
        "passengers": "23",
        "return_date": "22 avril",
        "special_needs": "non",
        "trip_type": "simple",
        "email": "non",
        "timestamp": "2025-04-18T15:54:08.483038"
    },
    {
        "departure": "l",
        "departure_date": "ll",
        "destination": "l",
        "group_type": "l",
        "passengers": "l",
        "return_date": "l",
        "special_needs": "l",
        "trip_type": "ll",
        "email": "l",
        "timestamp": "2025-04-18T15:58:15.592770"
    },
    {
        "departure": "Paris",
        "departure_date": "24 octobre",
        "destination": "Lyon",
        "group_type": "Entreprise",
        "passengers": "15",
        "return_date": "28 juillet",
        "special_needs": "NON",
        "trip_type": "Allez simple",
        "email": "kjekeek",
        "timestamp": "2025-04-18T16:07:07.620946"
    }
]